ecmodels/__init__.py
ecmodels/datasets.py
ecmodels/tests.py
ecmodels-0.1.dist-info/LICENSE
ecmodels-0.1.dist-info/METADATA
ecmodels-0.1.dist-info/WHEEL
ecmodels-0.1.dist-info/top_level.txt
ecmodels-0.1.dist-info/RECORD
