Metadata-Version: 2.1
Name: ecmodels
Version: 0.1
Summary: Econometric models and tests package.
Author: NeuralNine (Florian Dedov)
Author-email: <mail@neuralnine.com>
Keywords: econometrics,models,tests,regression
Classifier: Development Status :: 1 - Planning
Classifier: Intended Audience :: Developers
Classifier: Programming Language :: Python :: 3
Classifier: Operating System :: Unix
Classifier: Operating System :: MacOS :: MacOS X
Classifier: Operating System :: Microsoft :: Windows
License-File: LICENSE
Requires-Dist: pandas
Requires-Dist: numpy
Requires-Dist: scipy
Requires-Dist: matplotlib
